README.txt
setup.cfg
setup.py
docs/HISTORY.txt
docs/INSTALL.txt
docs/LICENSE.GPL
docs/LICENSE.txt
vs/__init__.py
vs.genericsetup.ldap.egg-info/PKG-INFO
vs.genericsetup.ldap.egg-info/SOURCES.txt
vs.genericsetup.ldap.egg-info/dependency_links.txt
vs.genericsetup.ldap.egg-info/entry_points.txt
vs.genericsetup.ldap.egg-info/namespace_packages.txt
vs.genericsetup.ldap.egg-info/not-zip-safe
vs.genericsetup.ldap.egg-info/requires.txt
vs.genericsetup.ldap.egg-info/top_level.txt
vs/genericsetup/__init__.py
vs/genericsetup/ldap/__init__.py
vs/genericsetup/ldap/configure.zcml
vs/genericsetup/ldap/exportimport.py
vs/genericsetup/ldap/interfaces.py
vs/genericsetup/ldap/tests.py
vs/genericsetup/ldap/version.txt
vs/genericsetup/ldap/xml/ldap_plugin.xml