Metadata-Version: 1.0
Name: vs.genericsetup.ldap
Version: 1.2
Summary: Extension for GenericSetup, support for LDAP and AD
Home-page: http://svn.plone.org/svn/collective/vs.genericsetup.ldap
Author: Andreas Jung
Author-email: info@zopyx.com
License: GPL
Keywords: Zope Plone Python LDAP AD GenericSetup
Platform: UNKNOWN
Classifier: Framework :: Plone
Classifier: Programming Language :: Python
Classifier: Topic :: Software Development :: Libraries :: Python Modules
